mcploader/__init__.py
mcploader/models.py
mcploader/py.typed
mcploader/utils.py
mcploader-0.1.0.dist-info/METADATA
mcploader-0.1.0.dist-info/WHEEL
mcploader-0.1.0.dist-info/top_level.txt
mcploader-0.1.0.dist-info/RECORD
