Metadata-Version: 2.4
Name: mcploader
Version: 0.1.0
Summary: This package is a small helper module that lets you define and consume multiple MCP servers (stdio, SSE, or Streamable HTTP) from a JSON configuration. It uses `pydantic-ai` MCP clients and validates configuration with Pydantic models.
Home-page: https://github.com/fswair/mcploader
Author: Mert Sirakaya
Author-email: contact@tomris.dev
License: MIT
Project-URL: Bug Reports, https://github.com/fswair/mcploader/issues
Project-URL: Source, https://github.com/fswair/mcploader
Keywords: mcp,mcp config management,pydantic-ai,mcp server,mcp client,mcp config,mcp servers
Classifier: Programming Language :: Python :: 3.10
Classifier: Programming Language :: Python :: 3.11
Classifier: Programming Language :: Python :: 3.12
Classifier: Programming Language :: Python :: 3.13
Classifier: License :: OSI Approved :: MIT License
Classifier: Operating System :: OS Independent
Classifier: Development Status :: 4 - Beta
Classifier: Intended Audience :: Developers
Classifier: Topic :: Software Development :: Libraries
Classifier: Topic :: Software Development :: Libraries :: Python Modules
Requires-Python: >=3.10
Requires-Dist: pydantic-ai
Requires-Dist: pydantic
Dynamic: author
Dynamic: author-email
Dynamic: classifier
Dynamic: description
Dynamic: description-content-type
Dynamic: home-page
Dynamic: keywords
Dynamic: license
Dynamic: project-url
Dynamic: requires-dist
Dynamic: requires-python
Dynamic: summary
